kew/__init__.py
kew/exceptions.py
kew/manager.py
kew/models.py
kew/py.typed
kew/tests/conftest.py
kew/tests/test_queue_manager.py
kew-0.1.5.dist-info/METADATA
kew-0.1.5.dist-info/WHEEL
kew-0.1.5.dist-info/RECORD
