Metadata-Version: 2.4
Name: kew
Version: 0.1.5
Summary: A flexible async task queue manager for Python applications
Project-URL: Homepage, https://github.com/justrach/kew
Project-URL: Bug Tracker, https://github.com/justrach/kew/issues
Author-email: Rach Pradhan <rach@rachit.ai>
Keywords: async,concurrent,manager,queue,redis,task
Classifier: Development Status :: 3 - Alpha
Classifier: Framework :: AsyncIO
Classifier: Intended Audience :: Developers
Classifier: License :: OSI Approved :: MIT License
Classifier: Operating System :: OS Independent
Classifier: Programming Language :: Python :: 3
Classifier: Topic :: Software Development :: Libraries :: Python Modules
Requires-Python: >=3.8
Requires-Dist: redis>=5.0.0
Provides-Extra: dev
Requires-Dist: black>=22.0.0; extra == 'dev'
Requires-Dist: isort>=5.0.0; extra == 'dev'
Requires-Dist: mypy>=1.0.0; extra == 'dev'
Requires-Dist: redis>=5.0.0; extra == 'dev'
Requires-Dist: ruff>=0.0.1; extra == 'dev'
Provides-Extra: test
Requires-Dist: coverage>=7.0.0; extra == 'test'
Requires-Dist: pytest-asyncio>=0.20.0; extra == 'test'
Requires-Dist: pytest-cov>=4.0.0; extra == 'test'
Requires-Dist: pytest-redis>=3.0.0; extra == 'test'
Requires-Dist: pytest>=7.0.0; extra == 'test'
Requires-Dist: redis>=5.0.0; extra == 'test'
